setup.py
generic_escape/__init__.py
generic_escape/tests.py
generic_escape/version.py
generic_escape.egg-info/PKG-INFO
generic_escape.egg-info/SOURCES.txt
generic_escape.egg-info/dependency_links.txt
generic_escape.egg-info/top_level.txt