Metadata-Version: 1.1
Name: generic-escape
Version: 1.1.3
Summary: A simple library for escaping and unescaping strings
Home-page: https://hydra.ecd.space/f/generic_escape/
Author: Eduard Christian Dumitrescu
Author-email: UNKNOWN
License: LGPLv3
Platform: UNKNOWN
Classifier: Programming Language :: Python :: 3 :: Only
